btrip_mcp_server/__init__.py
btrip_mcp_server/server.py
btrip_mcp_server-0.2.5.dist-info/METADATA
btrip_mcp_server-0.2.5.dist-info/WHEEL
btrip_mcp_server-0.2.5.dist-info/entry_points.txt
btrip_mcp_server-0.2.5.dist-info/RECORD
