Metadata-Version: 2.4
Name: btrip-mcp-server
Version: 0.2.5
Summary: 这是一个最新的版本.支持很多动作
Author-email: 洒花 <zhangwenzhe.zwz@alibaba-inc.com>
Requires-Python: >=3.10
Requires-Dist: httpx-sse>=0.4.0
Requires-Dist: httpx>=0.28.1
Requires-Dist: mcp[cli]>=1.8.1
